{"bounds": [[8.0, 102.0], [24.0, 110.0]], "stats": {"mean_risk": 0.583, "max_risk": 0.997, "n_cells": 367, "n_high": 209}, "grid": [{"lat": 13.0, "lon": 102.0, "risk": 0.988, "t": 29.7, "h": 71, "w": 4.0, "p": 0.0, "n": 0.76}, {"lat": 13.5, "lon": 102.0, "risk": 0.928, "t": 29.8, "h": 64, "w": 5.5, "p": 0.0, "n": 0.68}, {"lat": 14.0, "lon": 102.0, "risk": 0.82, "t": 30.4, "h": 67, "w": 5.7, "p": 0.0, "n": 0.69}, {"lat": 14.5, "lon": 102.0, "risk": 0.906, "t": 26.3, "h": 75, "w": 3.1, "p": 0.0, "n": 0.61}, {"lat": 15.0, "lon": 102.0, "risk": 0.954, "t": 27.6, "h": 66, "w": 4.7, "p": 0.0, "n": 0.56}, {"lat": 15.5, "lon": 102.0, "risk": 0.798, "t": 27.5, "h": 64, "w": 5.5, "p": 0.0, "n": 0.49}, {"lat": 16.0, "lon": 102.0, "risk": 0.82, "t": 25.5, "h": 72, "w": 4.7, "p": 0.0, "n": 0.8}, {"lat": 16.5, "lon": 102.0, "risk": 0.915, "t": 25.9, "h": 71, "w": 5.3, "p": 0.0, "n": 0.68}, {"lat": 17.0, "lon": 102.0, "risk": 0.757, "t": 25.2, "h": 72, "w": 4.5, "p": 0.0, "n": 0.73}, {"lat": 17.5, "lon": 102.0, "risk": 0.803, "t": 25.1, "h": 72, "w": 5.2, "p": 0.3, "n": 0.73}, {"lat": 18.0, "lon": 102.0, "risk": 0.522, "t": 25.1, "h": 78, "w": 4.8, "p": 0.3, "n": 0.85}, {"lat": 18.5, "lon": 102.0, "risk": 0.871, "t": 25.5, "h": 81, "w": 4.2, "p": 0.0, "n": 0.84}, {"lat": 19.0, "lon": 102.0, "risk": 0.014, "t": 24.2, "h": 84, "w": 3.0, "p": 0.8, "n": 0.89}, {"lat": 19.5, "lon": 102.0, "risk": 0.047, "t": 23.2, "h": 81, "w": 4.0, "p": 0.1, "n": 0.85}, {"lat": 20.0, "lon": 102.0, "risk": 0.132, "t": 24.3, "h": 81, "w": 2.2, "p": 0.0, "n": 0.85}, {"lat": 20.5, "lon": 102.0, "risk": 0.085, "t": 22.5, "h": 83, "w": 2.6, "p": 0.1, "n": 0.75}, {"lat": 21.0, "lon": 102.0, "risk": 0.031, "t": 22.0, "h": 82, "w": 4.4, "p": 0.0, "n": 0.88}, {"lat": 21.5, "lon": 102.0, "risk": 0.016, "t": 22.3, "h": 80, "w": 6.6, "p": 0.1, "n": 0.88}, {"lat": 22.0, "lon": 102.0, "risk": 0.768, "t": 21.5, "h": 75, "w": 7.3, "p": 0.0, "n": 0.29}, {"lat": 22.5, "lon": 102.0, "risk": 0.973, "t": 21.4, "h": 74, "w": 5.9, "p": 0.1, "n": 0.79}, {"lat": 23.0, "lon": 102.0, "risk": 0.07, "t": 19.2, "h": 71, "w": 7.5, "p": 0.0, "n": 0.87}, {"lat": 23.5, "lon": 102.0, "risk": 0.974, "t": 20.3, "h": 71, "w": 7.9, "p": 0.1, "n": 0.75}, {"lat": 24.0, "lon": 102.0, "risk": 0.718, "t": 15.7, "h": 72, "w": 7.2, "p": 0.2, "n": 0.77}, {"lat": 12.5, "lon": 102.5, "risk": 0.797, "t": 30.6, "h": 69, "w": 3.5, "p": 0.0, "n": 0.83}, {"lat": 13.0, "lon": 102.5, "risk": 0.97, "t": 28.9, "h": 73, "w": 3.1, "p": 0.0, "n": 0.73}, {"lat": 13.5, "lon": 102.5, "risk": 0.969, "t": 29.8, "h": 62, "w": 5.2, "p": 0.0, "n": 0.8}, {"lat": 14.0, "lon": 102.5, "risk": 0.446, "t": 28.6, "h": 66, "w": 6.8, "p": 0.0, "n": 0.87}, {"lat": 14.5, "lon": 102.5, "risk": 0.848, "t": 27.2, "h": 71, "w": 5.1, "p": 0.0, "n": 0.64}, {"lat": 15.0, "lon": 102.5, "risk": 0.894, "t": 27.7, "h": 67, "w": 5.8, "p": 0.0, "n": 0.53}, {"lat": 15.5, "lon": 102.5, "risk": 0.823, "t": 27.8, "h": 66, "w": 5.4, "p": 0.0, "n": 0.4}, {"lat": 16.0, "lon": 102.5, "risk": 0.958, "t": 27.4, "h": 66, "w": 6.0, "p": 0.0, "n": 0.59}, {"lat": 16.5, "lon": 102.5, "risk": 0.84, "t": 26.9, "h": 70, "w": 4.6, "p": 0.0, "n": 0.45}, {"lat": 17.0, "lon": 102.5, "risk": 0.694, "t": 26.3, "h": 71, "w": 4.5, "p": 0.0, "n": 0.82}, {"lat": 17.5, "lon": 102.5, "risk": 0.744, "t": 26.1, "h": 70, "w": 6.0, "p": 0.0, "n": 0.63}, {"lat": 18.0, "lon": 102.5, "risk": 0.961, "t": 26.1, "h": 75, "w": 5.1, "p": 0.0, "n": 0.57}, {"lat": 18.5, "lon": 102.5, "risk": 0.983, "t": 26.0, "h": 78, "w": 4.5, "p": 0.0, "n": 0.76}, {"lat": 19.0, "lon": 102.5, "risk": 0.029, "t": 24.2, "h": 84, "w": 4.0, "p": 0.9, "n": 0.83}, {"lat": 19.5, "lon": 102.5, "risk": 0.047, "t": 21.7, "h": 84, "w": 4.8, "p": 0.5, "n": 0.8}, {"lat": 20.0, "lon": 102.5, "risk": 0.033, "t": 22.7, "h": 81, "w": 3.3, "p": 0.0, "n": 0.83}, {"lat": 20.5, "lon": 102.5, "risk": 0.438, "t": 24.2, "h": 81, "w": 0.5, "p": 0.0, "n": 0.84}, {"lat": 21.0, "lon": 102.5, "risk": 0.016, "t": 21.9, "h": 83, "w": 3.0, "p": 0.0, "n": 0.89}, {"lat": 21.5, "lon": 102.5, "risk": 0.107, "t": 22.0, "h": 79, "w": 5.4, "p": 0.0, "n": 0.83}, {"lat": 22.0, "lon": 102.5, "risk": 0.038, "t": 20.3, "h": 77, "w": 5.9, "p": 0.0, "n": 0.89}, {"lat": 22.5, "lon": 102.5, "risk": 0.783, "t": 22.5, "h": 72, "w": 5.2, "p": 0.0, "n": 0.38}, {"lat": 23.0, "lon": 102.5, "risk": 0.803, "t": 18.5, "h": 71, "w": 6.7, "p": 0.2, "n": 0.76}, {"lat": 23.5, "lon": 102.5, "risk": 0.351, "t": 17.3, "h": 69, "w": 9.2, "p": 0.0, "n": 0.84}, {"lat": 24.0, "lon": 102.5, "risk": 0.104, "t": 15.2, "h": 72, "w": 13.6, "p": 0.1, "n": 0.82}, {"lat": 12.0, "lon": 103.0, "risk": 0.016, "t": 26.8, "h": 73, "w": 3.9, "p": 0.0, "n": 0.87}, {"lat": 12.5, "lon": 103.0, "risk": 0.534, "t": 26.0, "h": 75, "w": 2.9, "p": 0.0, "n": 0.82}, {"lat": 13.0, "lon": 103.0, "risk": 0.383, "t": 30.2, "h": 66, "w": 3.5, "p": 0.0, "n": 0.5}, {"lat": 13.5, "lon": 103.0, "risk": 0.259, "t": 30.3, "h": 61, "w": 6.3, "p": 0.0, "n": 0.77}, {"lat": 14.0, "lon": 103.0, "risk": 0.833, "t": 29.8, "h": 63, "w": 8.3, "p": 0.0, "n": 0.58}, {"lat": 14.5, "lon": 103.0, "risk": 0.582, "t": 28.1, "h": 68, "w": 7.1, "p": 0.0, "n": 0.52}, {"lat": 15.0, "lon": 103.0, "risk": 0.833, "t": 27.8, "h": 67, "w": 5.6, "p": 0.0, "n": 0.39}, {"lat": 15.5, "lon": 103.0, "risk": 0.709, "t": 27.9, "h": 66, "w": 6.3, "p": 0.0, "n": 0.41}, {"lat": 16.0, "lon": 103.0, "risk": 0.798, "t": 27.4, "h": 67, "w": 5.9, "p": 0.0, "n": 0.39}, {"lat": 16.5, "lon": 103.0, "risk": 0.783, "t": 28.1, "h": 64, "w": 4.0, "p": 0.0, "n": 0.53}, {"lat": 17.0, "lon": 103.0, "risk": 0.864, "t": 27.8, "h": 65, "w": 2.5, "p": 0.0, "n": 0.32}, {"lat": 17.5, "lon": 103.0, "risk": 0.905, "t": 27.7, "h": 64, "w": 5.0, "p": 0.0, "n": 0.5}, {"lat": 18.0, "lon": 103.0, "risk": 0.83, "t": 27.7, "h": 65, "w": 5.8, "p": 0.0, "n": 0.46}, {"lat": 18.5, "lon": 103.0, "risk": 0.811, "t": 25.9, "h": 77, "w": 3.4, "p": 0.4, "n": 0.79}, {"lat": 19.0, "lon": 103.0, "risk": 0.004, "t": 21.2, "h": 85, "w": 2.7, "p": 0.6, "n": 0.88}, {"lat": 19.5, "lon": 103.0, "risk": 0.065, "t": 21.7, "h": 82, "w": 4.7, "p": 0.4, "n": 0.68}, {"lat": 20.0, "lon": 103.0, "risk": 0.031, "t": 23.1, "h": 79, "w": 3.4, "p": 0.0, "n": 0.85}, {"lat": 20.5, "lon": 103.0, "risk": 0.102, "t": 23.4, "h": 81, "w": 4.9, "p": 0.0, "n": 0.84}, {"lat": 21.0, "lon": 103.0, "risk": 0.012, "t": 20.9, "h": 82, "w": 4.8, "p": 0.0, "n": 0.89}, {"lat": 21.5, "lon": 103.0, "risk": 0.069, "t": 21.6, "h": 80, "w": 5.9, "p": 0.0, "n": 0.88}, {"lat": 22.0, "lon": 103.0, "risk": 0.041, "t": 21.7, "h": 78, "w": 3.4, "p": 0.0, "n": 0.87}, {"lat": 22.5, "lon": 103.0, "risk": 0.176, "t": 18.4, "h": 73, "w": 5.4, "p": 0.1, "n": 0.96}, {"lat": 23.0, "lon": 103.0, "risk": 0.908, "t": 15.8, "h": 72, "w": 5.7, "p": 0.1, "n": 0.71}, {"lat": 23.5, "lon": 103.0, "risk": 0.261, "t": 15.8, "h": 73, "w": 11.0, "p": 0.1, "n": 0.69}, {"lat": 24.0, "lon": 103.0, "risk": 0.123, "t": 17.6, "h": 70, "w": 12.9, "p": 0.1, "n": 0.6}, {"lat": 11.5, "lon": 103.5, "risk": 0.039, "t": 30.1, "h": 65, "w": 3.4, "p": 0.0, "n": 0.87}, {"lat": 12.0, "lon": 103.5, "risk": 0.017, "t": 23.8, "h": 81, "w": 1.9, "p": 0.1, "n": 0.88}, {"lat": 12.5, "lon": 103.5, "risk": 0.828, "t": 28.4, "h": 77, "w": 5.5, "p": 0.1, "n": 0.52}, {"lat": 13.0, "lon": 103.5, "risk": 0.313, "t": 29.9, "h": 68, "w": 5.7, "p": 0.0, "n": 0.44}, {"lat": 13.5, "lon": 103.5, "risk": 0.039, "t": 30.4, "h": 63, "w": 4.5, "p": 0.0, "n": 0.48}, {"lat": 14.0, "lon": 103.5, "risk": 0.14, "t": 30.6, "h": 61, "w": 8.4, "p": 0.0, "n": 0.49}, {"lat": 14.5, "lon": 103.5, "risk": 0.607, "t": 28.2, "h": 68, "w": 7.3, "p": 0.0, "n": 0.47}, {"lat": 15.0, "lon": 103.5, "risk": 0.765, "t": 28.2, "h": 67, "w": 5.8, "p": 0.0, "n": 0.39}, {"lat": 15.5, "lon": 103.5, "risk": 0.886, "t": 28.2, "h": 65, "w": 7.0, "p": 0.0, "n": 0.38}, {"lat": 16.0, "lon": 103.5, "risk": 0.862, "t": 28.1, "h": 64, "w": 7.0, "p": 0.0, "n": 0.44}, {"lat": 16.5, "lon": 103.5, "risk": 0.943, "t": 28.1, "h": 64, "w": 5.8, "p": 0.0, "n": 0.78}, {"lat": 17.0, "lon": 103.5, "risk": 0.805, "t": 27.8, "h": 62, "w": 4.6, "p": 0.0, "n": 0.4}, {"lat": 17.5, "lon": 103.5, "risk": 0.512, "t": 28.4, "h": 59, "w": 5.3, "p": 0.0, "n": 0.45}, {"lat": 18.0, "lon": 103.5, "risk": 0.929, "t": 28.4, "h": 59, "w": 7.0, "p": 0.0, "n": 0.75}, {"lat": 18.5, "lon": 103.5, "risk": 0.612, "t": 25.6, "h": 68, "w": 5.7, "p": 0.0, "n": 0.85}, {"lat": 19.0, "lon": 103.5, "risk": 0.95, "t": 25.7, "h": 77, "w": 4.0, "p": 0.1, "n": 0.67}, {"lat": 19.5, "lon": 103.5, "risk": 0.139, "t": 21.7, "h": 85, "w": 1.8, "p": 0.1, "n": 0.74}, {"lat": 20.0, "lon": 103.5, "risk": 0.081, "t": 21.3, "h": 82, "w": 2.4, "p": 0.0, "n": 0.71}, {"lat": 20.5, "lon": 103.5, "risk": 0.102, "t": 21.8, "h": 81, "w": 5.4, "p": 0.0, "n": 0.81}, {"lat": 21.0, "lon": 103.5, "risk": 0.181, "t": 20.7, "h": 80, "w": 4.5, "p": 0.0, "n": 0.77}, {"lat": 21.5, "lon": 103.5, "risk": 0.055, "t": 20.3, "h": 81, "w": 3.1, "p": 0.0, "n": 0.85}, {"lat": 22.0, "lon": 103.5, "risk": 0.972, "t": 21.0, "h": 78, "w": 3.9, "p": 0.0, "n": 0.78}, {"lat": 22.5, "lon": 103.5, "risk": 0.541, "t": 19.4, "h": 76, "w": 3.5, "p": 0.0, "n": 0.69}, {"lat": 23.0, "lon": 103.5, "risk": 0.142, "t": 20.9, "h": 78, "w": 5.8, "p": 0.2, "n": 0.83}, {"lat": 23.5, "lon": 103.5, "risk": 0.031, "t": 16.2, "h": 79, "w": 13.1, "p": 0.0, "n": 0.62}, {"lat": 24.0, "lon": 103.5, "risk": 0.374, "t": 19.4, "h": 70, "w": 15.5, "p": 0.0, "n": 0.76}, {"lat": 11.0, "lon": 104.0, "risk": 0.305, "t": 28.8, "h": 67, "w": 4.6, "p": 0.0, "n": 0.83}, {"lat": 11.5, "lon": 104.0, "risk": 0.61, "t": 27.4, "h": 73, "w": 3.6, "p": 0.0, "n": 0.86}, {"lat": 12.0, "lon": 104.0, "risk": 0.867, "t": 27.1, "h": 79, "w": 3.8, "p": 0.0, "n": 0.83}, {"lat": 12.5, "lon": 104.0, "risk": 0.933, "t": 28.4, "h": 76, "w": 6.0, "p": 0.0, "n": 0.51}, {"lat": 13.0, "lon": 104.0, "risk": 0.446, "t": 28.3, "h": 69, "w": 9.2, "p": 0.0, "n": null}, {"lat": 13.5, "lon": 104.0, "risk": 0.38, "t": 30.8, "h": 63, "w": 4.7, "p": 0.0, "n": 0.54}, {"lat": 14.0, "lon": 104.0, "risk": 0.962, "t": 29.6, "h": 64, "w": 4.1, "p": 0.0, "n": 0.62}, {"lat": 14.5, "lon": 104.0, "risk": 0.603, "t": 28.2, "h": 69, "w": 6.1, "p": 0.0, "n": 0.57}, {"lat": 15.0, "lon": 104.0, "risk": 0.968, "t": 28.4, "h": 67, "w": 5.9, "p": 0.0, "n": 0.76}, {"lat": 15.5, "lon": 104.0, "risk": 0.553, "t": 28.4, "h": 65, "w": 7.9, "p": 0.0, "n": 0.36}, {"lat": 16.0, "lon": 104.0, "risk": 0.765, "t": 28.3, "h": 64, "w": 8.5, "p": 0.0, "n": 0.37}, {"lat": 16.5, "lon": 104.0, "risk": 0.865, "t": 27.9, "h": 64, "w": 7.3, "p": 0.0, "n": 0.48}, {"lat": 17.0, "lon": 104.0, "risk": 0.914, "t": 26.8, "h": 67, "w": 4.8, "p": 0.0, "n": 0.73}, {"lat": 17.5, "lon": 104.0, "risk": 0.614, "t": 28.3, "h": 62, "w": 5.8, "p": 0.0, "n": 0.53}, {"lat": 18.0, "lon": 104.0, "risk": 0.887, "t": 28.9, "h": 60, "w": 3.0, "p": 0.0, "n": 0.77}, {"lat": 18.5, "lon": 104.0, "risk": 0.853, "t": 27.9, "h": 65, "w": 2.3, "p": 0.0, "n": 0.77}, {"lat": 19.0, "lon": 104.0, "risk": 0.257, "t": 21.5, "h": 80, "w": 1.5, "p": 0.0, "n": 0.81}, {"lat": 19.5, "lon": 104.0, "risk": 0.096, "t": 19.5, "h": 87, "w": 1.8, "p": 0.0, "n": 0.8}, {"lat": 20.0, "lon": 104.0, "risk": 0.175, "t": 20.5, "h": 84, "w": 3.9, "p": 0.0, "n": 0.78}, {"lat": 20.5, "lon": 104.0, "risk": 0.041, "t": 20.9, "h": 82, "w": 4.1, "p": 0.0, "n": 0.89}, {"lat": 21.0, "lon": 104.0, "risk": 0.529, "t": 22.0, "h": 79, "w": 2.6, "p": 0.0, "n": 0.67}, {"lat": 21.5, "lon": 104.0, "risk": 0.836, "t": 22.6, "h": 74, "w": 4.9, "p": 0.0, "n": 0.74}, {"lat": 22.0, "lon": 104.0, "risk": 0.816, "t": 19.7, "h": 78, "w": 4.0, "p": 0.0, "n": 0.6}, {"lat": 22.5, "lon": 104.0, "risk": 0.898, "t": 22.3, "h": 80, "w": 2.0, "p": 0.0, "n": 0.61}, {"lat": 23.0, "lon": 104.0, "risk": 0.03, "t": 17.0, "h": 82, "w": 8.3, "p": 0.1, "n": 0.83}, {"lat": 23.5, "lon": 104.0, "risk": 0.07, "t": 17.7, "h": 79, "w": 14.5, "p": 0.0, "n": 0.76}, {"lat": 24.0, "lon": 104.0, "risk": 0.005, "t": 15.8, "h": 77, "w": 18.8, "p": 0.0, "n": 0.65}, {"lat": 10.5, "lon": 104.5, "risk": 0.047, "t": 30.6, "h": 65, "w": 8.4, "p": 0.0, "n": 0.64}, {"lat": 11.0, "lon": 104.5, "risk": 0.89, "t": 30.1, "h": 64, "w": 7.0, "p": 0.0, "n": 0.53}, {"lat": 11.5, "lon": 104.5, "risk": 0.758, "t": 30.2, "h": 69, "w": 5.8, "p": 0.0, "n": 0.46}, {"lat": 12.0, "lon": 104.5, "risk": 0.948, "t": 29.7, "h": 74, "w": 6.0, "p": 0.0, "n": 0.74}, {"lat": 12.5, "lon": 104.5, "risk": 0.855, "t": 29.7, "h": 75, "w": 6.6, "p": 0.0, "n": -0.02}, {"lat": 13.0, "lon": 104.5, "risk": 0.078, "t": 30.9, "h": 68, "w": 4.1, "p": 0.0, "n": 0.65}, {"lat": 13.5, "lon": 104.5, "risk": 0.918, "t": 30.4, "h": 63, "w": 4.0, "p": 0.0, "n": 0.64}, {"lat": 14.0, "lon": 104.5, "risk": 0.965, "t": 29.2, "h": 67, "w": 4.7, "p": 0.0, "n": 0.78}, {"lat": 14.5, "lon": 104.5, "risk": 0.975, "t": 27.9, "h": 70, "w": 4.8, "p": 0.0, "n": 0.77}, {"lat": 15.0, "lon": 104.5, "risk": 0.482, "t": 28.5, "h": 68, "w": 6.2, "p": 0.0, "n": 0.52}, {"lat": 15.5, "lon": 104.5, "risk": 0.513, "t": 28.5, "h": 67, "w": 9.7, "p": 0.0, "n": 0.45}, {"lat": 16.0, "lon": 104.5, "risk": 0.644, "t": 28.1, "h": 67, "w": 10.8, "p": 0.0, "n": 0.37}, {"lat": 16.5, "lon": 104.5, "risk": 0.767, "t": 27.2, "h": 68, "w": 8.9, "p": 0.0, "n": 0.57}, {"lat": 17.0, "lon": 104.5, "risk": 0.908, "t": 27.6, "h": 68, "w": 6.0, "p": 0.0, "n": 0.45}, {"lat": 17.5, "lon": 104.5, "risk": 0.872, "t": 29.1, "h": 61, "w": 4.1, "p": 0.0, "n": 0.41}, {"lat": 18.0, "lon": 104.5, "risk": 0.919, "t": 27.4, "h": 66, "w": 2.9, "p": 0.0, "n": 0.79}, {"lat": 18.5, "lon": 104.5, "risk": 0.89, "t": 23.4, "h": 77, "w": 4.2, "p": 0.0, "n": 0.74}, {"lat": 19.0, "lon": 104.5, "risk": 0.057, "t": 19.0, "h": 86, "w": 1.2, "p": 0.0, "n": 0.76}, {"lat": 19.5, "lon": 104.5, "risk": 0.453, "t": 19.3, "h": 87, "w": 3.6, "p": 0.0, "n": 0.49}, {"lat": 20.0, "lon": 104.5, "risk": 0.261, "t": 19.3, "h": 87, "w": 3.7, "p": 0.0, "n": 0.62}, {"lat": 20.5, "lon": 104.5, "risk": 0.914, "t": 21.9, "h": 82, "w": 3.1, "p": 0.1, "n": 0.72}, {"lat": 21.0, "lon": 104.5, "risk": 0.368, "t": 21.5, "h": 79, "w": 2.2, "p": 0.0, "n": 0.84}, {"lat": 21.5, "lon": 104.5, "risk": 0.192, "t": 19.2, "h": 83, "w": 2.6, "p": 0.1, "n": 0.72}, {"lat": 22.0, "lon": 104.5, "risk": 0.687, "t": 20.2, "h": 79, "w": 0.4, "p": 0.2, "n": 0.83}, {"lat": 22.5, "lon": 104.5, "risk": 0.742, "t": 18.5, "h": 75, "w": 4.2, "p": 0.0, "n": 0.47}, {"lat": 23.0, "lon": 104.5, "risk": 0.009, "t": 16.7, "h": 82, "w": 8.5, "p": 0.0, "n": 0.46}, {"lat": 23.5, "lon": 104.5, "risk": 0.003, "t": 18.2, "h": 79, "w": 13.6, "p": 0.0, "n": 0.37}, {"lat": 24.0, "lon": 104.5, "risk": 0.006, "t": 18.4, "h": 76, "w": 20.0, "p": 0.0, "n": 0.6}, {"lat": 9.0, "lon": 105.0, "risk": 0.723, "t": 30.1, "h": 77, "w": 6.9, "p": 0.0, "n": 0.38}, {"lat": 9.5, "lon": 105.0, "risk": 0.914, "t": 29.7, "h": 80, "w": 6.0, "p": 0.1, "n": 0.7}, {"lat": 10.5, "lon": 105.0, "risk": 0.17, "t": 30.6, "h": 65, "w": 5.8, "p": 0.0, "n": 0.83}, {"lat": 11.0, "lon": 105.0, "risk": 0.271, "t": 30.8, "h": 64, "w": 8.0, "p": 0.0, "n": -0.08}, {"lat": 11.5, "lon": 105.0, "risk": 0.15, "t": 30.5, "h": 67, "w": 7.3, "p": 0.0, "n": 0.54}, {"lat": 12.0, "lon": 105.0, "risk": 0.054, "t": 30.8, "h": 66, "w": 6.1, "p": 0.0, "n": 0.43}, {"lat": 12.5, "lon": 105.0, "risk": 0.092, "t": 30.7, "h": 68, "w": 3.7, "p": 0.0, "n": 0.09}, {"lat": 13.0, "lon": 105.0, "risk": 0.545, "t": 30.8, "h": 68, "w": 2.1, "p": 0.0, "n": 0.52}, {"lat": 13.5, "lon": 105.0, "risk": 0.7, "t": 31.6, "h": 62, "w": 4.0, "p": 0.0, "n": 0.55}, {"lat": 14.0, "lon": 105.0, "risk": 0.88, "t": 30.4, "h": 62, "w": 5.9, "p": 0.0, "n": 0.69}, {"lat": 14.5, "lon": 105.0, "risk": 0.886, "t": 29.1, "h": 65, "w": 5.9, "p": 0.0, "n": 0.54}, {"lat": 15.0, "lon": 105.0, "risk": 0.698, "t": 29.5, "h": 66, "w": 5.8, "p": 0.0, "n": 0.45}, {"lat": 15.5, "lon": 105.0, "risk": 0.726, "t": 29.4, "h": 67, "w": 10.0, "p": 0.0, "n": 0.63}, {"lat": 16.0, "lon": 105.0, "risk": 0.878, "t": 28.1, "h": 69, "w": 11.5, "p": 0.0, "n": 0.69}, {"lat": 16.5, "lon": 105.0, "risk": 0.945, "t": 27.3, "h": 69, "w": 8.8, "p": 0.0, "n": 0.69}, {"lat": 17.0, "lon": 105.0, "risk": 0.899, "t": 27.9, "h": 67, "w": 6.4, "p": 0.0, "n": 0.49}, {"lat": 17.5, "lon": 105.0, "risk": 0.254, "t": 27.1, "h": 68, "w": 3.1, "p": 0.0, "n": 0.86}, {"lat": 18.0, "lon": 105.0, "risk": 0.478, "t": 23.1, "h": 78, "w": 4.1, "p": 0.0, "n": 0.84}, {"lat": 18.5, "lon": 105.0, "risk": 0.04, "t": 18.3, "h": 88, "w": 1.2, "p": 0.1, "n": 0.75}, {"lat": 19.0, "lon": 105.0, "risk": 0.648, "t": 19.9, "h": 82, "w": 3.9, "p": 0.1, "n": 0.57}, {"lat": 19.5, "lon": 105.0, "risk": 0.683, "t": 19.2, "h": 86, "w": 4.4, "p": 0.1, "n": 0.78}, {"lat": 20.0, "lon": 105.0, "risk": 0.478, "t": 18.8, "h": 87, "w": 3.8, "p": 0.0, "n": 0.67}, {"lat": 20.5, "lon": 105.0, "risk": 0.144, "t": 20.4, "h": 83, "w": 4.3, "p": 0.1, "n": 0.84}, {"lat": 21.0, "lon": 105.0, "risk": 0.743, "t": 20.9, "h": 81, "w": 4.9, "p": 0.0, "n": 0.79}, {"lat": 21.5, "lon": 105.0, "risk": 0.995, "t": 21.1, "h": 77, "w": 4.7, "p": 0.0, "n": 0.71}, {"lat": 22.0, "lon": 105.0, "risk": 0.984, "t": 20.6, "h": 73, "w": 5.2, "p": 0.0, "n": 0.76}, {"lat": 22.5, "lon": 105.0, "risk": 0.49, "t": 19.7, "h": 71, "w": 4.6, "p": 0.1, "n": 0.87}, {"lat": 23.0, "lon": 105.0, "risk": 0.784, "t": 17.9, "h": 76, "w": 5.6, "p": 0.1, "n": 0.76}, {"lat": 23.5, "lon": 105.0, "risk": 0.029, "t": 17.2, "h": 83, "w": 11.0, "p": 0.0, "n": 0.49}, {"lat": 24.0, "lon": 105.0, "risk": 0.487, "t": 19.6, "h": 78, "w": 12.3, "p": 0.0, "n": 0.69}, {"lat": 9.5, "lon": 105.5, "risk": 0.471, "t": 29.9, "h": 78, "w": 4.3, "p": 0.0, "n": 0.36}, {"lat": 10.0, "lon": 105.5, "risk": 0.464, "t": 30.2, "h": 78, "w": 5.1, "p": 0.0, "n": 0.35}, {"lat": 10.5, "lon": 105.5, "risk": 0.509, "t": 31.1, "h": 68, "w": 0.7, "p": 0.0, "n": 0.25}, {"lat": 11.0, "lon": 105.5, "risk": 0.352, "t": 31.2, "h": 63, "w": 7.1, "p": 0.0, "n": 0.67}, {"lat": 11.5, "lon": 105.5, "risk": 0.014, "t": 31.1, "h": 62, "w": 7.8, "p": 0.0, "n": 0.58}, {"lat": 12.0, "lon": 105.5, "risk": 0.073, "t": 30.4, "h": 65, "w": 6.2, "p": 0.0, "n": 0.52}, {"lat": 12.5, "lon": 105.5, "risk": 0.506, "t": 30.6, "h": 65, "w": 3.0, "p": 0.0, "n": 0.86}, {"lat": 13.0, "lon": 105.5, "risk": 0.894, "t": 30.9, "h": 62, "w": 1.1, "p": 0.0, "n": 0.77}, {"lat": 13.5, "lon": 105.5, "risk": 0.76, "t": 31.2, "h": 62, "w": 3.1, "p": 0.0, "n": 0.76}, {"lat": 14.0, "lon": 105.5, "risk": 0.384, "t": 31.2, "h": 62, "w": 1.9, "p": 0.0, "n": 0.84}, {"lat": 14.5, "lon": 105.5, "risk": 0.313, "t": 29.5, "h": 64, "w": 4.1, "p": 0.0, "n": 0.87}, {"lat": 15.0, "lon": 105.5, "risk": 0.379, "t": 29.9, "h": 64, "w": 4.4, "p": 0.0, "n": 0.77}, {"lat": 15.5, "lon": 105.5, "risk": 0.549, "t": 30.4, "h": 64, "w": 7.6, "p": 0.0, "n": 0.67}, {"lat": 16.0, "lon": 105.5, "risk": 0.661, "t": 28.2, "h": 70, "w": 9.0, "p": 0.0, "n": 0.61}, {"lat": 16.5, "lon": 105.5, "risk": 0.849, "t": 26.4, "h": 71, "w": 10.2, "p": 0.0, "n": 0.51}, {"lat": 17.0, "lon": 105.5, "risk": 0.547, "t": 25.2, "h": 75, "w": 6.6, "p": 0.0, "n": 0.87}, {"lat": 17.5, "lon": 105.5, "risk": 0.983, "t": 24.1, "h": 77, "w": 5.1, "p": 0.0, "n": 0.74}, {"lat": 18.0, "lon": 105.5, "risk": 0.017, "t": 18.6, "h": 89, "w": 2.7, "p": 0.2, "n": 0.82}, {"lat": 18.5, "lon": 105.5, "risk": 0.227, "t": 19.7, "h": 84, "w": 5.0, "p": 0.7, "n": 0.43}, {"lat": 19.0, "lon": 105.5, "risk": 0.917, "t": 21.0, "h": 78, "w": 6.6, "p": 0.1, "n": 0.41}, {"lat": 19.5, "lon": 105.5, "risk": 0.912, "t": 20.3, "h": 83, "w": 4.7, "p": 0.1, "n": 0.81}, {"lat": 20.0, "lon": 105.5, "risk": 0.975, "t": 20.8, "h": 81, "w": 6.2, "p": 0.0, "n": 0.61}, {"lat": 20.5, "lon": 105.5, "risk": 0.954, "t": 20.3, "h": 80, "w": 7.2, "p": 0.0, "n": 0.56}, {"lat": 21.0, "lon": 105.5, "risk": 0.989, "t": 21.5, "h": 78, "w": 6.8, "p": 0.0, "n": 0.6}, {"lat": 21.5, "lon": 105.5, "risk": 0.989, "t": 20.6, "h": 75, "w": 7.2, "p": 0.0, "n": 0.59}, {"lat": 22.0, "lon": 105.5, "risk": 0.84, "t": 20.3, "h": 74, "w": 6.0, "p": 0.0, "n": 0.82}, {"lat": 22.5, "lon": 105.5, "risk": 0.502, "t": 19.4, "h": 72, "w": 6.1, "p": 0.1, "n": 0.88}, {"lat": 23.0, "lon": 105.5, "risk": 0.939, "t": 18.2, "h": 74, "w": 6.3, "p": 0.1, "n": 0.8}, {"lat": 23.5, "lon": 105.5, "risk": 0.055, "t": 16.7, "h": 82, "w": 9.1, "p": 0.0, "n": 0.79}, {"lat": 24.0, "lon": 105.5, "risk": 0.618, "t": 20.2, "h": 79, "w": 4.5, "p": 0.0, "n": 0.66}, {"lat": 9.5, "lon": 106.0, "risk": 0.782, "t": 28.8, "h": 78, "w": 9.8, "p": 0.0, "n": 0.86}, {"lat": 10.0, "lon": 106.0, "risk": 0.941, "t": 29.7, "h": 81, "w": 4.8, "p": 0.0, "n": 0.75}, {"lat": 10.5, "lon": 106.0, "risk": 0.82, "t": 31.0, "h": 74, "w": 5.2, "p": 0.0, "n": 0.59}, {"lat": 11.0, "lon": 106.0, "risk": 0.286, "t": 31.1, "h": 64, "w": 5.6, "p": 0.0, "n": 0.55}, {"lat": 11.5, "lon": 106.0, "risk": 0.045, "t": 31.1, "h": 62, "w": 6.6, "p": 0.0, "n": 0.43}, {"lat": 12.0, "lon": 106.0, "risk": 0.627, "t": 30.8, "h": 65, "w": 5.6, "p": 0.0, "n": 0.61}, {"lat": 12.5, "lon": 106.0, "risk": 0.73, "t": 29.9, "h": 70, "w": 5.8, "p": 0.0, "n": 0.1}, {"lat": 13.0, "lon": 106.0, "risk": 0.645, "t": 30.4, "h": 66, "w": 2.1, "p": 0.0, "n": 0.7}, {"lat": 13.5, "lon": 106.0, "risk": 0.638, "t": 31.1, "h": 64, "w": 4.3, "p": 0.0, "n": 0.71}, {"lat": 14.0, "lon": 106.0, "risk": 0.579, "t": 31.0, "h": 65, "w": 6.0, "p": 0.0, "n": 0.77}, {"lat": 14.5, "lon": 106.0, "risk": 0.033, "t": 30.1, "h": 66, "w": 3.6, "p": 0.0, "n": 0.89}, {"lat": 15.0, "lon": 106.0, "risk": 0.88, "t": 29.4, "h": 76, "w": 3.7, "p": 0.0, "n": 0.83}, {"lat": 15.5, "lon": 106.0, "risk": 0.906, "t": 29.1, "h": 70, "w": 3.4, "p": 0.0, "n": 0.78}, {"lat": 16.0, "lon": 106.0, "risk": 0.87, "t": 27.2, "h": 73, "w": 4.7, "p": 0.0, "n": 0.83}, {"lat": 16.5, "lon": 106.0, "risk": 0.891, "t": 24.4, "h": 77, "w": 7.7, "p": 0.0, "n": 0.76}, {"lat": 17.0, "lon": 106.0, "risk": 0.955, "t": 22.1, "h": 80, "w": 7.5, "p": 0.0, "n": 0.78}, {"lat": 17.5, "lon": 106.0, "risk": 0.037, "t": 18.7, "h": 90, "w": 5.8, "p": 0.0, "n": 0.4}, {"lat": 18.0, "lon": 106.0, "risk": 0.406, "t": 19.9, "h": 83, "w": 7.5, "p": 0.2, "n": 0.13}, {"lat": 20.0, "lon": 106.0, "risk": 0.809, "t": 21.3, "h": 77, "w": 2.2, "p": 0.1, "n": 0.65}, {"lat": 20.5, "lon": 106.0, "risk": 0.628, "t": 21.7, "h": 78, "w": 6.2, "p": 0.0, "n": 0.43}, {"lat": 21.0, "lon": 106.0, "risk": 0.408, "t": 21.8, "h": 75, "w": 7.7, "p": 0.0, "n": 0.51}, {"lat": 21.5, "lon": 106.0, "risk": 0.955, "t": 21.3, "h": 74, "w": 7.3, "p": 0.0, "n": 0.55}, {"lat": 22.0, "lon": 106.0, "risk": 0.947, "t": 19.9, "h": 73, "w": 7.0, "p": 0.0, "n": 0.85}, {"lat": 22.5, "lon": 106.0, "risk": 0.777, "t": 18.9, "h": 75, "w": 6.9, "p": 0.0, "n": 0.86}, {"lat": 23.0, "lon": 106.0, "risk": 0.68, "t": 17.7, "h": 77, "w": 8.6, "p": 0.1, "n": 0.81}, {"lat": 23.5, "lon": 106.0, "risk": 0.556, "t": 18.0, "h": 78, "w": 8.3, "p": 0.0, "n": 0.73}, {"lat": 24.0, "lon": 106.0, "risk": 0.728, "t": 19.1, "h": 77, "w": 3.1, "p": 0.0, "n": 0.85}, {"lat": 10.0, "lon": 106.5, "risk": 0.357, "t": 28.6, "h": 80, "w": 7.7, "p": 0.0, "n": 0.51}, {"lat": 10.5, "lon": 106.5, "risk": 0.795, "t": 30.3, "h": 79, "w": 6.5, "p": 0.0, "n": 0.59}, {"lat": 11.0, "lon": 106.5, "risk": 0.079, "t": 30.8, "h": 70, "w": 5.6, "p": 0.0, "n": 0.62}, {"lat": 11.5, "lon": 106.5, "risk": 0.49, "t": 30.7, "h": 66, "w": 5.8, "p": 0.0, "n": 0.67}, {"lat": 12.0, "lon": 106.5, "risk": 0.755, "t": 30.9, "h": 65, "w": 5.1, "p": 0.0, "n": 0.41}, {"lat": 12.5, "lon": 106.5, "risk": 0.514, "t": 30.2, "h": 64, "w": 10.9, "p": 0.0, "n": 0.87}, {"lat": 13.0, "lon": 106.5, "risk": 0.548, "t": 30.7, "h": 62, "w": 9.0, "p": 0.0, "n": 0.69}, {"lat": 13.5, "lon": 106.5, "risk": 0.476, "t": 30.9, "h": 64, "w": 3.7, "p": 0.0, "n": 0.31}, {"lat": 14.0, "lon": 106.5, "risk": 0.539, "t": 32.2, "h": 62, "w": 5.9, "p": 0.0, "n": 0.83}, {"lat": 14.5, "lon": 106.5, "risk": 0.229, "t": 31.2, "h": 62, "w": 2.0, "p": 0.0, "n": 0.85}, {"lat": 15.0, "lon": 106.5, "risk": 0.027, "t": 27.9, "h": 72, "w": 1.9, "p": 0.2, "n": 0.86}, {"lat": 15.5, "lon": 106.5, "risk": 0.528, "t": 27.1, "h": 73, "w": 2.0, "p": 0.0, "n": 0.81}, {"lat": 16.0, "lon": 106.5, "risk": 0.06, "t": 26.3, "h": 76, "w": 3.6, "p": 0.0, "n": 0.88}, {"lat": 16.5, "lon": 106.5, "risk": 0.764, "t": 21.5, "h": 88, "w": 8.1, "p": 0.2, "n": 0.77}, {"lat": 17.0, "lon": 106.5, "risk": 0.008, "t": 18.9, "h": 93, "w": 5.0, "p": 1.0, "n": 0.55}, {"lat": 17.5, "lon": 106.5, "risk": 0.695, "t": 20.6, "h": 84, "w": 12.7, "p": 1.6, "n": 0.76}, {"lat": 20.5, "lon": 106.5, "risk": 0.703, "t": 21.1, "h": 76, "w": 5.4, "p": 0.0, "n": 0.32}, {"lat": 21.0, "lon": 106.5, "risk": 0.599, "t": 21.8, "h": 75, "w": 8.1, "p": 0.0, "n": 0.52}, {"lat": 21.5, "lon": 106.5, "risk": 0.984, "t": 21.1, "h": 75, "w": 7.0, "p": 0.0, "n": 0.73}, {"lat": 22.0, "lon": 106.5, "risk": 0.842, "t": 19.8, "h": 77, "w": 7.2, "p": 0.0, "n": 0.76}, {"lat": 22.5, "lon": 106.5, "risk": 0.961, "t": 19.8, "h": 75, "w": 7.3, "p": 0.0, "n": 0.87}, {"lat": 23.0, "lon": 106.5, "risk": 0.453, "t": 17.4, "h": 78, "w": 9.9, "p": 0.0, "n": 0.75}, {"lat": 23.5, "lon": 106.5, "risk": 0.172, "t": 17.7, "h": 80, "w": 9.2, "p": 0.0, "n": 0.78}, {"lat": 24.0, "lon": 106.5, "risk": 0.967, "t": 19.1, "h": 75, "w": 3.5, "p": 0.0, "n": 0.72}, {"lat": 10.5, "lon": 107.0, "risk": 0.92, "t": 29.7, "h": 78, "w": 5.0, "p": 0.0, "n": null}, {"lat": 11.0, "lon": 107.0, "risk": 0.99, "t": 30.0, "h": 79, "w": 4.9, "p": 0.0, "n": 0.75}, {"lat": 11.5, "lon": 107.0, "risk": 0.932, "t": 30.5, "h": 68, "w": 3.6, "p": 0.0, "n": 0.72}, {"lat": 12.0, "lon": 107.0, "risk": 0.314, "t": 30.0, "h": 65, "w": 5.1, "p": 0.0, "n": 0.85}, {"lat": 12.5, "lon": 107.0, "risk": 0.923, "t": 27.5, "h": 70, "w": 13.4, "p": 0.0, "n": 0.77}, {"lat": 13.0, "lon": 107.0, "risk": 0.748, "t": 29.4, "h": 64, "w": 10.3, "p": 0.0, "n": 0.59}, {"lat": 13.5, "lon": 107.0, "risk": 0.186, "t": 31.3, "h": 60, "w": 7.6, "p": 0.0, "n": 0.64}, {"lat": 14.0, "lon": 107.0, "risk": 0.49, "t": 31.8, "h": 61, "w": 2.8, "p": 0.0, "n": 0.77}, {"lat": 14.5, "lon": 107.0, "risk": 0.203, "t": 27.9, "h": 68, "w": 2.0, "p": 0.0, "n": 0.86}, {"lat": 15.0, "lon": 107.0, "risk": 0.276, "t": 29.6, "h": 66, "w": 2.9, "p": 0.0, "n": 0.84}, {"lat": 15.5, "lon": 107.0, "risk": 0.819, "t": 24.8, "h": 76, "w": 5.1, "p": 0.3, "n": 0.77}, {"lat": 16.0, "lon": 107.0, "risk": 0.026, "t": 21.4, "h": 86, "w": 4.9, "p": 2.3, "n": 0.86}, {"lat": 16.5, "lon": 107.0, "risk": 0.003, "t": 19.9, "h": 95, "w": 4.0, "p": 5.1, "n": 0.51}, {"lat": 17.0, "lon": 107.0, "risk": 0.22, "t": 21.6, "h": 90, "w": 4.0, "p": 10.0, "n": 0.65}, {"lat": 21.0, "lon": 107.0, "risk": 0.962, "t": 20.8, "h": 76, "w": 7.4, "p": 0.0, "n": 0.11}, {"lat": 21.5, "lon": 107.0, "risk": 0.976, "t": 20.5, "h": 78, "w": 6.8, "p": 0.0, "n": 0.83}, {"lat": 22.0, "lon": 107.0, "risk": 0.641, "t": 20.3, "h": 77, "w": 5.0, "p": 0.0, "n": 0.75}, {"lat": 22.5, "lon": 107.0, "risk": 0.833, "t": 19.3, "h": 74, "w": 6.1, "p": 0.0, "n": 0.82}, {"lat": 23.0, "lon": 107.0, "risk": 0.384, "t": 17.7, "h": 75, "w": 9.6, "p": 0.0, "n": 0.87}, {"lat": 23.5, "lon": 107.0, "risk": 0.769, "t": 18.9, "h": 77, "w": 8.3, "p": 0.0, "n": 0.8}, {"lat": 24.0, "lon": 107.0, "risk": 0.967, "t": 17.5, "h": 75, "w": 7.0, "p": 0.0, "n": 0.8}, {"lat": 11.0, "lon": 107.5, "risk": 0.981, "t": 29.8, "h": 81, "w": 3.4, "p": 0.1, "n": 0.86}, {"lat": 11.5, "lon": 107.5, "risk": 0.982, "t": 30.3, "h": 78, "w": 3.8, "p": 0.0, "n": 0.7}, {"lat": 12.0, "lon": 107.5, "risk": 0.926, "t": 26.7, "h": 74, "w": 9.3, "p": 0.1, "n": 0.71}, {"lat": 12.5, "lon": 107.5, "risk": 0.017, "t": 24.3, "h": 81, "w": 9.0, "p": 0.2, "n": 0.87}, {"lat": 13.0, "lon": 107.5, "risk": 0.849, "t": 28.3, "h": 68, "w": 7.4, "p": 0.1, "n": 0.83}, {"lat": 13.5, "lon": 107.5, "risk": 0.873, "t": 30.1, "h": 64, "w": 6.5, "p": 0.0, "n": 0.83}, {"lat": 14.0, "lon": 107.5, "risk": 0.467, "t": 31.0, "h": 61, "w": 3.3, "p": 0.0, "n": 0.67}, {"lat": 14.5, "lon": 107.5, "risk": 0.007, "t": 27.7, "h": 70, "w": 1.1, "p": 0.0, "n": 0.88}, {"lat": 15.0, "lon": 107.5, "risk": 0.066, "t": 22.5, "h": 79, "w": 5.6, "p": 0.1, "n": 0.86}, {"lat": 15.5, "lon": 107.5, "risk": 0.001, "t": 19.4, "h": 94, "w": 2.7, "p": 5.7, "n": 0.46}, {"lat": 16.0, "lon": 107.5, "risk": 0.002, "t": 18.8, "h": 96, "w": 1.0, "p": 6.0, "n": 0.79}, {"lat": 16.5, "lon": 107.5, "risk": 0.694, "t": 22.3, "h": 90, "w": 3.4, "p": 6.9, "n": 0.13}, {"lat": 21.0, "lon": 107.5, "risk": 0.782, "t": 19.4, "h": 71, "w": 10.9, "p": 0.0, "n": 0.29}, {"lat": 21.5, "lon": 107.5, "risk": 0.134, "t": 18.8, "h": 76, "w": 4.8, "p": 0.0, "n": 0.88}, {"lat": 22.0, "lon": 107.5, "risk": 0.613, "t": 20.4, "h": 79, "w": 4.4, "p": 0.0, "n": 0.79}, {"lat": 22.5, "lon": 107.5, "risk": 0.769, "t": 19.7, "h": 75, "w": 4.5, "p": 0.0, "n": 0.78}, {"lat": 23.0, "lon": 107.5, "risk": 0.844, "t": 18.5, "h": 75, "w": 7.5, "p": 0.0, "n": 0.73}, {"lat": 23.5, "lon": 107.5, "risk": 0.851, "t": 18.3, "h": 74, "w": 7.6, "p": 0.0, "n": 0.63}, {"lat": 24.0, "lon": 107.5, "risk": 0.881, "t": 17.6, "h": 75, "w": 9.5, "p": 0.0, "n": 0.73}, {"lat": 11.0, "lon": 108.0, "risk": 0.984, "t": 29.3, "h": 78, "w": 0.9, "p": 0.0, "n": 0.72}, {"lat": 11.5, "lon": 108.0, "risk": 0.044, "t": 26.1, "h": 81, "w": 2.6, "p": 0.1, "n": 0.86}, {"lat": 12.0, "lon": 108.0, "risk": 0.111, "t": 25.5, "h": 80, "w": 5.2, "p": 0.1, "n": 0.88}, {"lat": 12.5, "lon": 108.0, "risk": 0.673, "t": 25.3, "h": 80, "w": 6.4, "p": 0.4, "n": 0.45}, {"lat": 13.0, "lon": 108.0, "risk": 0.824, "t": 26.5, "h": 74, "w": 11.1, "p": 0.1, "n": 0.71}, {"lat": 13.5, "lon": 108.0, "risk": 0.903, "t": 26.7, "h": 73, "w": 11.6, "p": 0.1, "n": 0.8}, {"lat": 14.0, "lon": 108.0, "risk": 0.731, "t": 24.9, "h": 74, "w": 12.3, "p": 0.1, "n": 0.73}, {"lat": 14.5, "lon": 108.0, "risk": 0.876, "t": 24.9, "h": 75, "w": 6.3, "p": 0.0, "n": 0.74}, {"lat": 15.0, "lon": 108.0, "risk": 0.002, "t": 17.7, "h": 93, "w": 4.6, "p": 3.2, "n": 0.77}, {"lat": 15.5, "lon": 108.0, "risk": 0.082, "t": 21.4, "h": 94, "w": 1.6, "p": 8.0, "n": 0.82}, {"lat": 16.0, "lon": 108.0, "risk": 0.004, "t": 21.3, "h": 92, "w": 0.2, "p": 7.2, "n": 0.2}, {"lat": 22.0, "lon": 108.0, "risk": 0.895, "t": 18.9, "h": 74, "w": 5.6, "p": 0.0, "n": 0.73}, {"lat": 22.5, "lon": 108.0, "risk": 0.894, "t": 19.9, "h": 73, "w": 6.8, "p": 0.0, "n": 0.72}, {"lat": 23.0, "lon": 108.0, "risk": 0.884, "t": 19.7, "h": 72, "w": 5.8, "p": 0.0, "n": 0.49}, {"lat": 23.5, "lon": 108.0, "risk": 0.733, "t": 18.4, "h": 73, "w": 8.1, "p": 0.0, "n": 0.84}, {"lat": 24.0, "lon": 108.0, "risk": 0.88, "t": 17.9, "h": 72, "w": 9.6, "p": 0.0, "n": 0.7}, {"lat": 11.5, "lon": 108.5, "risk": 0.258, "t": 26.1, "h": 75, "w": 4.5, "p": 0.0, "n": 0.86}, {"lat": 12.0, "lon": 108.5, "risk": 0.011, "t": 21.0, "h": 88, "w": 6.2, "p": 0.3, "n": 0.71}, {"lat": 12.5, "lon": 108.5, "risk": 0.045, "t": 22.6, "h": 89, "w": 4.3, "p": 3.0, "n": 0.77}, {"lat": 13.0, "lon": 108.5, "risk": 0.317, "t": 23.6, "h": 85, "w": 7.2, "p": 1.4, "n": 0.57}, {"lat": 13.5, "lon": 108.5, "risk": 0.94, "t": 25.0, "h": 81, "w": 7.0, "p": 0.4, "n": 0.65}, {"lat": 14.0, "lon": 108.5, "risk": 0.68, "t": 23.3, "h": 85, "w": 8.8, "p": 0.7, "n": 0.76}, {"lat": 14.5, "lon": 108.5, "risk": 0.017, "t": 19.9, "h": 92, "w": 6.9, "p": 4.2, "n": 0.8}, {"lat": 15.0, "lon": 108.5, "risk": 0.047, "t": 22.5, "h": 94, "w": 2.0, "p": 8.9, "n": 0.29}, {"lat": 15.5, "lon": 108.5, "risk": 0.9, "t": 23.9, "h": 88, "w": 2.3, "p": 8.4, "n": 0.12}, {"lat": 22.0, "lon": 108.5, "risk": 0.989, "t": 20.1, "h": 72, "w": 6.9, "p": 0.0, "n": 0.76}, {"lat": 22.5, "lon": 108.5, "risk": 0.967, "t": 19.9, "h": 71, "w": 6.2, "p": 0.0, "n": 0.71}, {"lat": 23.0, "lon": 108.5, "risk": 0.937, "t": 19.1, "h": 69, "w": 5.9, "p": 0.0, "n": 0.75}, {"lat": 23.5, "lon": 108.5, "risk": 0.793, "t": 17.3, "h": 70, "w": 5.1, "p": 0.0, "n": 0.78}, {"lat": 24.0, "lon": 108.5, "risk": 0.582, "t": 17.9, "h": 71, "w": 8.6, "p": 0.0, "n": 0.56}, {"lat": 12.0, "lon": 109.0, "risk": 0.236, "t": 23.5, "h": 84, "w": 5.5, "p": 1.6, "n": 0.74}, {"lat": 12.5, "lon": 109.0, "risk": 0.663, "t": 25.4, "h": 86, "w": 2.5, "p": 2.0, "n": 0.7}, {"lat": 13.0, "lon": 109.0, "risk": 0.911, "t": 25.4, "h": 90, "w": 3.1, "p": 5.5, "n": 0.62}, {"lat": 13.5, "lon": 109.0, "risk": 0.754, "t": 24.5, "h": 88, "w": 5.0, "p": 3.8, "n": 0.71}, {"lat": 14.0, "lon": 109.0, "risk": 0.915, "t": 24.8, "h": 87, "w": 6.0, "p": 4.6, "n": 0.44}, {"lat": 14.5, "lon": 109.0, "risk": 0.942, "t": 23.8, "h": 89, "w": 15.0, "p": 7.1, "n": 0.8}, {"lat": 18.5, "lon": 109.0, "risk": 0.806, "t": 25.0, "h": 76, "w": 8.0, "p": 0.1, "n": 0.51}, {"lat": 19.0, "lon": 109.0, "risk": 0.932, "t": 24.9, "h": 79, "w": 2.4, "p": 0.1, "n": 0.04}, {"lat": 19.5, "lon": 109.0, "risk": 0.945, "t": 24.1, "h": 74, "w": 14.9, "p": 0.0, "n": 0.72}, {"lat": 22.0, "lon": 109.0, "risk": 0.997, "t": 21.2, "h": 65, "w": 5.1, "p": 0.0, "n": 0.77}, {"lat": 22.5, "lon": 109.0, "risk": 0.995, "t": 20.4, "h": 67, "w": 4.8, "p": 0.0, "n": 0.72}, {"lat": 23.0, "lon": 109.0, "risk": 0.982, "t": 19.4, "h": 68, "w": 4.5, "p": 0.0, "n": 0.72}, {"lat": 23.5, "lon": 109.0, "risk": 0.982, "t": 19.1, "h": 67, "w": 4.0, "p": 0.0, "n": 0.77}, {"lat": 24.0, "lon": 109.0, "risk": 0.779, "t": 17.7, "h": 64, "w": 7.7, "p": 0.0, "n": 0.7}, {"lat": 18.5, "lon": 109.5, "risk": 0.06, "t": 22.8, "h": 78, "w": 1.8, "p": 0.0, "n": 0.89}, {"lat": 19.0, "lon": 109.5, "risk": 0.04, "t": 19.9, "h": 88, "w": 2.3, "p": 0.2, "n": 0.86}, {"lat": 19.5, "lon": 109.5, "risk": 0.933, "t": 22.9, "h": 79, "w": 8.3, "p": 0.1, "n": 0.59}, {"lat": 22.0, "lon": 109.5, "risk": 0.995, "t": 21.7, "h": 64, "w": 5.8, "p": 0.0, "n": 0.71}, {"lat": 22.5, "lon": 109.5, "risk": 0.98, "t": 20.2, "h": 68, "w": 4.6, "p": 0.0, "n": 0.82}, {"lat": 23.0, "lon": 109.5, "risk": 0.871, "t": 19.8, "h": 68, "w": 3.2, "p": 0.0, "n": 0.54}, {"lat": 23.5, "lon": 109.5, "risk": 0.983, "t": 19.0, "h": 66, "w": 5.0, "p": 0.0, "n": 0.69}, {"lat": 24.0, "lon": 109.5, "risk": 0.975, "t": 19.0, "h": 67, "w": 5.9, "p": 0.0, "n": 0.61}, {"lat": 18.5, "lon": 110.0, "risk": 0.981, "t": 23.4, "h": 79, "w": 14.7, "p": 0.2, "n": 0.47}, {"lat": 19.0, "lon": 110.0, "risk": 0.474, "t": 20.9, "h": 87, "w": 1.7, "p": 0.5, "n": 0.79}, {"lat": 19.5, "lon": 110.0, "risk": 0.992, "t": 22.5, "h": 79, "w": 4.7, "p": 0.1, "n": 0.8}, {"lat": 20.5, "lon": 110.0, "risk": 0.971, "t": 22.3, "h": 75, "w": 11.1, "p": 0.0, "n": 0.57}, {"lat": 21.0, "lon": 110.0, "risk": 0.992, "t": 21.6, "h": 71, "w": 10.3, "p": 0.0, "n": 0.66}, {"lat": 21.5, "lon": 110.0, "risk": 0.927, "t": 22.3, "h": 64, "w": 9.7, "p": 0.0, "n": 0.57}, {"lat": 22.0, "lon": 110.0, "risk": 0.985, "t": 21.7, "h": 62, "w": 6.9, "p": 0.0, "n": 0.61}, {"lat": 22.5, "lon": 110.0, "risk": 0.984, "t": 20.4, "h": 64, "w": 4.6, "p": 0.0, "n": 0.59}, {"lat": 23.0, "lon": 110.0, "risk": 0.983, "t": 20.0, "h": 65, "w": 3.2, "p": 0.0, "n": 0.6}, {"lat": 23.5, "lon": 110.0, "risk": 0.248, "t": 18.4, "h": 68, "w": 3.6, "p": 0.0, "n": 0.87}, {"lat": 24.0, "lon": 110.0, "risk": 0.966, "t": 17.5, "h": 69, "w": 4.6, "p": 0.0, "n": 0.86}]}